streamlit_mdm_table/__init__.py
streamlit_mdm_table/example.py
streamlit_mdm_table/frontend/build/asset-manifest.json
streamlit_mdm_table/frontend/build/bootstrap.min.css
streamlit_mdm_table/frontend/build/index.html
streamlit_mdm_table/frontend/build/static/js/main.038c53bb.js
streamlit_mdm_table/frontend/build/static/js/main.038c53bb.js.LICENSE.txt
streamlit_mdm_table/frontend/build/static/js/main.038c53bb.js.map
streamlit_mdm_table/frontend/build/static/js/main.0f402f47.js
streamlit_mdm_table/frontend/build/static/js/main.0f402f47.js.LICENSE.txt
streamlit_mdm_table/frontend/build/static/js/main.0f402f47.js.map
streamlit_mdm_table/frontend/build/static/js/main.0f5df087.js
streamlit_mdm_table/frontend/build/static/js/main.0f5df087.js.LICENSE.txt
streamlit_mdm_table/frontend/build/static/js/main.0f5df087.js.map
streamlit_mdm_table/frontend/build/static/js/main.13630268.js
streamlit_mdm_table/frontend/build/static/js/main.13630268.js.LICENSE.txt
streamlit_mdm_table/frontend/build/static/js/main.13630268.js.map
streamlit_mdm_table/frontend/build/static/js/main.1f578799.js
streamlit_mdm_table/frontend/build/static/js/main.1f578799.js.LICENSE.txt
streamlit_mdm_table/frontend/build/static/js/main.1f578799.js.map
streamlit_mdm_table/frontend/build/static/js/main.4458f6e0.js
streamlit_mdm_table/frontend/build/static/js/main.4458f6e0.js.LICENSE.txt
streamlit_mdm_table/frontend/build/static/js/main.4458f6e0.js.map
streamlit_mdm_table/frontend/build/static/js/main.50a0660b.js
streamlit_mdm_table/frontend/build/static/js/main.50a0660b.js.LICENSE.txt
streamlit_mdm_table/frontend/build/static/js/main.50a0660b.js.map
streamlit_mdm_table/frontend/build/static/js/main.5c34acc8.js
streamlit_mdm_table/frontend/build/static/js/main.5c34acc8.js.LICENSE.txt
streamlit_mdm_table/frontend/build/static/js/main.5c34acc8.js.map
streamlit_mdm_table/frontend/build/static/js/main.a3473f1b.js
streamlit_mdm_table/frontend/build/static/js/main.a3473f1b.js.LICENSE.txt
ex_pro_streamlit_mdm_table-0.0.9.dist-info/LICENSE
ex_pro_streamlit_mdm_table-0.0.9.dist-info/METADATA
ex_pro_streamlit_mdm_table-0.0.9.dist-info/WHEEL
ex_pro_streamlit_mdm_table-0.0.9.dist-info/top_level.txt
ex_pro_streamlit_mdm_table-0.0.9.dist-info/RECORD
