Metadata-Version: 2.1
Name: ex-pro-streamlit-mdm-table
Version: 0.0.9
Summary: Streamlit component that allows for easy management of task mapping. Specific to a project. Do not use. For demonstration purposes only.
Home-page: 
Author: Jack Labbe
Author-email: jlabbe@eigenx.com
Requires-Python: >=3.7
License-File: LICENSE
Requires-Dist: streamlit >=0.63
Requires-Dist: pandas >=1.1.5
Requires-Dist: numpy >=1.19.5
Requires-Dist: pyarrow >=5.0.0
Provides-Extra: devel
Requires-Dist: wheel ; extra == 'devel'
Requires-Dist: pytest ==7.4.0 ; extra == 'devel'
Requires-Dist: playwright ==1.39.0 ; extra == 'devel'
Requires-Dist: requests ==2.31.0 ; extra == 'devel'
Requires-Dist: pytest-playwright-snapshot ==1.0 ; extra == 'devel'
Requires-Dist: pytest-rerunfailures ==12.0 ; extra == 'devel'
